LICENSE
MANIFEST.in
README.md
setup.py
confluent_kafka_smyte/__init__.py
confluent_kafka_smyte.egg-info/PKG-INFO
confluent_kafka_smyte.egg-info/SOURCES.txt
confluent_kafka_smyte.egg-info/dependency_links.txt
confluent_kafka_smyte.egg-info/top_level.txt
confluent_kafka_smyte/kafkatest/__init__.py
confluent_kafka_smyte/kafkatest/verifiable_client.py
confluent_kafka_smyte/kafkatest/verifiable_consumer.py
confluent_kafka_smyte/kafkatest/verifiable_producer.py
confluent_kafka_smyte/src/Consumer.c
confluent_kafka_smyte/src/Producer.c
confluent_kafka_smyte/src/confluent_kafka_smyte.c
confluent_kafka_smyte/src/confluent_kafka_smyte.h