Metadata-Version: 1.0
Name: confluent-kafka-smyte
Version: 0.9.3
Summary: Smyte fork of Confluent's Apache Kafka client for Python
Home-page: https://github.com/smyte-forks/confluent-kafka-python
Author: Confluent Inc
Author-email: support@confluent.io
License: UNKNOWN
Platform: UNKNOWN
